goodgoodstudy/__init__.py
goodgoodstudy-0.0.1.dist-info/METADATA
goodgoodstudy-0.0.1.dist-info/WHEEL
goodgoodstudy-0.0.1.dist-info/entry_points.txt
goodgoodstudy-0.0.1.dist-info/top_level.txt
goodgoodstudy-0.0.1.dist-info/RECORD
