Metadata-Version: 2.1
Name: goodgoodstudy
Version: 0.0.1
Summary: 好好学习
Home-page: https://github.com/gyk001
Author: gyk001
Author-email: gyk001@gmail.com
License: UNKNOWN
Platform: UNKNOWN
